{
    "page_content": [
        {
            "section_name": "Section 6.9",
            "parent_section_name": "[missing]",
            "text": "TMAs to be expanded July 2024",
            "image_diagram_summary": "[missing]",
            "contains_image_diagam": "false",
            "contains_table": "false"
        },
        {
            "section_name": "Section 6.11",
            "parent_section_name": "[missing]",
            "text": "Traffic volume requirements modified",
            "image_diagram_summary": "[missing]",
            "contains_image_diagam": "false",
            "contains_table": "false"
        },
        {
            "section_name": "Section 6.15",
            "parent_section_name": "[missing]",
            "text": "New section \u2013 Traffic Cones and Bollards",
            "image_diagram_summary": "[missing]",
            "contains_image_diagam": "false",
            "contains_table": "false"
        },
        {
            "section_name": "Section 6.16",
            "parent_section_name": "[missing]",
            "text": "Speed Feedback Signs section relocated",
            "image_diagram_summary": "[missing]",
            "contains_image_diagam": "false",
            "contains_table": "false"
        },
        {
            "section_name": "Section 6.17",
            "parent_section_name": "[missing]",
            "text": "New section \u2013 Approach Tapers",
            "image_diagram_summary": "[missing]",
            "contains_image_diagam": "false",
            "contains_table": "false"
        },
        {
            "section_name": "Section 6.18",
            "parent_section_name": "[missing]",
            "text": "New section \u2013 Emergency Lanes and Vehicle Breakdowns",
            "image_diagram_summary": "[missing]",
            "contains_image_diagam": "false",
            "contains_table": "false"
        },
        {
            "section_name": "Section 6.19",
            "parent_section_name": "[missing]",
            "text": "New section - Smart Freeways",
            "image_diagram_summary": "[missing]",
            "contains_image_diagam": "false",
            "contains_table": "false"
        },
        {
            "section_name": "Section 6.20",
            "parent_section_name": "[missing]",
            "text": "New section - Worksite Access",
            "image_diagram_summary": "[missing]",
            "contains_image_diagam": "false",
            "contains_table": "false"
        },
        {
            "section_name": "Sections 8.2 and 8.3",
            "parent_section_name": "[missing]",
            "text": "RIIWHS201D removed from prerequisites",
            "image_diagram_summary": "[missing]",
            "contains_image_diagam": "false",
            "contains_table": "false"
        },
        {
            "section_name": "Section 8.7",
            "parent_section_name": "[missing]",
            "text": "OTMA perquisites updated",
            "image_diagram_summary": "[missing]",
            "contains_image_diagam": "false",
            "contains_table": "false"
        },
        {
            "section_name": "Appendix 1",
            "parent_section_name": "[missing]",
            "text": "Definitions added for Long Term Works, High Speed Roads, High Volume Roads Road definition updated",
            "image_diagram_summary": "[missing]",
            "contains_image_diagam": "false",
            "contains_table": "false"
        },
        {
            "section_name": "Appendix 4",
            "parent_section_name": "[missing]",
            "text": "Pilbara Region email updated",
            "image_diagram_summary": "[missing]",
            "contains_image_diagam": "false",
            "contains_table": "false"
        },
        {
            "section_name": "Appendix 5",
            "parent_section_name": "[missing]",
            "text": "MMS-REG-15 added",
            "image_diagram_summary": "[missing]",
            "contains_image_diagam": "false",
            "contains_table": "false"
        },
        {
            "section_name": "Section 2.1.2 and 5.2",
            "parent_section_name": "September 2023",
            "text": "Video drive through requirements added",
            "image_diagram_summary": "[missing]",
            "contains_image_diagam": "false",
            "contains_table": "false"
        },
        {
            "section_name": "Section 6.3.1",
            "parent_section_name": "September 2023",
            "text": "Updates to requirements for securing signs",
            "image_diagram_summary": "[missing]",
            "contains_image_diagam": "false",
            "contains_table": "false"
        },
        {
            "section_name": "Section 6.1.11",
            "parent_section_name": "May 2023",
            "text": "New section \u2013 U-Turn DETOUR Ahead Signs",
            "image_diagram_summary": "[missing]",
            "contains_image_diagam": "false",
            "contains_table": "false"
        },
        {
            "section_name": "Section 6.2.4",
            "parent_section_name": "May 2023",
            "text": "New section \u2013 Selection and Use of MMS",
            "image_diagram_summary": "[missing]",
            "contains_image_diagam": "false",
            "contains_table": "false"
        },
        {
            "section_name": "Appendix 5",
            "parent_section_name": "May 2023",
            "text": "MMS-ADV-31 may be used in either side of the frame MMS-DIV-10 added",
            "image_diagram_summary": "[missing]",
            "contains_image_diagam": "false",
            "contains_table": "false"
        },
        {
            "section_name": "[missing]",
            "parent_section_name": "March 2023",
            "text": "Shall updated to must",
            "image_diagram_summary": "[missing]",
            "contains_image_diagam": "false",
            "contains_table": "false"
        },
        {
            "section_name": "[missing]",
            "parent_section_name": "March 2023",
            "text": "Figure numbers modified",
            "image_diagram_summary": "[missing]",
            "contains_image_diagam": "false",
            "contains_table": "false"
        },
        {
            "section_name": "[missing]",
            "parent_section_name": "March 2023",
            "text": "Table numbers modified",
            "image_diagram_summary": "[missing]",
            "contains_image_diagam": "false",
            "contains_table": "false"
        },
        {
            "section_name": "Section 1.3.2",
            "parent_section_name": "March 2023",
            "text": "Austroads Training Framework adoption updated",
            "image_diagram_summary": "[missing]",
            "contains_image_diagam": "false",
            "contains_table": "false"
        },
        {
            "section_name": "Section 2.4",
            "parent_section_name": "March 2023",
            "text": "New section \u2013 Traffic Modelling",
            "image_diagram_summary": "[missing]",
            "contains_image_diagam": "false",
            "contains_table": "false"
        },
        {
            "section_name": "Section 4.2.1",
            "parent_section_name": "March 2023",
            "text": "Details added for TMPs at major projects",
            "image_diagram_summary": "[missing]",
            "contains_image_diagam": "false",
            "contains_table": "false"
        }
    ],
    "page_header": "OFFICIAL",
    "page_footer": "[missing]",
    "page_number": "[missing]",
    "document_title": "Traffic Management for Works on Roads - Code of Practice",
    "document_summary": "The 'Traffic Management for Works on Roads: Code of Practice' by Main Roads Western Australia provides comprehensive guidelines for managing traffic during road works. It emphasizes the importance of safety for both road users and workers, detailing the responsibilities of various authorities and the necessary procedures for implementing Traffic Management Plans (TMPs). The document includes specific requirements for temporary signage, traffic control devices, and risk management, as well as the use of Truck Mounted Attenuators (TMAs) and other safety measures. It also outlines accreditation requirements for traffic management personnel and provides detailed inventories and application schedules for various road signs.",
    "page_sequence_number": 5
}