{
    "page_content": [
        {
            "section_name": "REGULATORY SERIES SIGNS",
            "parent_section_name": "[missing]",
            "text": "<table><tr><th>REG</th><th>Sign</th><th>Code</th><th>Size (mm)</th><th>Description</th></tr><tr><td>REG</td><td><img src='Buses Excepted'></td><td>MMS-REG-8</td><td>1200 x 300</td><td>BUSES EXCEPTED</td></tr><tr><td>REG</td><td><img src='Bicycles Excepted'></td><td>MMS-REG-9</td><td>1200 x 300</td><td>BICYCLES EXCEPTED</td></tr><tr><td>REG</td><td><img src='Authorised Vehicles Excepted'></td><td>MMS-REG-10</td><td>600 x 600</td><td>AUTHORISED VEHICLES EXCEPTED</td></tr><tr><td>REG</td><td><img src='Buses and Taxis Excepted'></td><td>MMS-REG-11</td><td>600 x 600</td><td>BUSES AND TAXIS EXCEPTED</td></tr><tr><td>REG</td><td><img src='Buses and Bicycles Excepted'></td><td>MMS-REG-12</td><td>600 x 600</td><td>BUSES AND BICYCLES EXCEPTED</td></tr><tr><td>REG</td><td><img src='At Street Name'></td><td>MMS-REG-13</td><td>600 x 600</td><td>AT STREET NAME</td></tr><tr><td>REG</td><td><img src='Bicycle Lane Closed'></td><td>MMS-REG-14</td><td>600 x 600</td><td>BICYCLE LANE CLOSED (SYMBOLIC)</td></tr><tr><td>REG</td><td><img src='Stop Here on Red Signal'></td><td>MMS-REG-15</td><td>1200 x 600</td><td>STOP HERE ON RED SIGNAL</td></tr></table>",
            "image_diagram_summary": "[missing]",
            "contains_image_diagam": "true",
            "contains_table": "true"
        }
    ],
    "page_header": "OFFICIAL",
    "page_footer": "Multi-Message Sign Inventory and Application Schedule",
    "page_number": "22",
    "document_title": "Traffic Management for Works on Roads - Code of Practice",
    "document_summary": "The 'Traffic Management for Works on Roads: Code of Practice' by Main Roads Western Australia provides comprehensive guidelines for managing traffic during road works. It emphasizes the importance of safety for both road users and workers, detailing the responsibilities of various authorities and the necessary procedures for implementing Traffic Management Plans (TMPs). The document includes specific requirements for temporary signage, traffic control devices, and risk management, as well as the use of Truck Mounted Attenuators (TMAs) and other safety measures. It also outlines accreditation requirements for traffic management personnel and provides detailed inventories and application schedules for various road signs.",
    "page_sequence_number": 123
}